certbot_dns_shellrent/__init__.py
certbot_dns_shellrent/dns_shellrent.py
certbot_dns_shellrent/dns_shellrent_test.py
certbot_dns_shellrent-0.1.1.dist-info/LICENSE.txt
certbot_dns_shellrent-0.1.1.dist-info/METADATA
certbot_dns_shellrent-0.1.1.dist-info/WHEEL
certbot_dns_shellrent-0.1.1.dist-info/entry_points.txt
certbot_dns_shellrent-0.1.1.dist-info/top_level.txt
certbot_dns_shellrent-0.1.1.dist-info/RECORD
