Metadata-Version: 2.1
Name: certbot-dns-shellrent
Version: 0.1.1
Summary: shellrent DNS Authenticator plugin for Certbot
Home-page: https://github.com/shellrent/certbot-dns-shellrent
Author: Shellrent
Author-email: info@shellrent.com
License: Apache License 2.0
Classifier: Development Status :: 5 - Production/Stable
Classifier: Environment :: Plugins
Classifier: Intended Audience :: System Administrators
Classifier: License :: OSI Approved :: Apache Software License
Classifier: Operating System :: POSIX :: Linux
Classifier: Programming Language :: Python
Classifier: Programming Language :: Python :: 2
Classifier: Programming Language :: Python :: 2.7
Classifier: Programming Language :: Python :: 3
Classifier: Programming Language :: Python :: 3.4
Classifier: Programming Language :: Python :: 3.5
Classifier: Programming Language :: Python :: 3.6
Classifier: Programming Language :: Python :: 3.7
Classifier: Programming Language :: Python :: 3.8
Classifier: Programming Language :: Python :: 3.9
Classifier: Topic :: Internet :: WWW/HTTP
Classifier: Topic :: Security
Classifier: Topic :: System :: Installation/Setup
Classifier: Topic :: System :: Networking
Classifier: Topic :: System :: Systems Administration
Classifier: Topic :: Utilities
Requires-Python: >=2.7, !=3.0.*, !=3.1.*, !=3.2.*, !=3.3.*
License-File: LICENSE.txt
Requires-Dist: acme (>=0.29.0)
Requires-Dist: certbot (>=0.34.0)
Requires-Dist: setuptools
Requires-Dist: requests
Requires-Dist: mock
Requires-Dist: requests-mock
